Metadata-Version: 2.1
Name: encrypid
Version: 0.1.4
Summary: Uma ferramenta para encriptar e decriptar credenciais de forma segura.
Home-page: https://github.com/hqr90/encrypid
Author: Hilton Queiroz Rebello
Author-email: rebello.hiltonqueiroz@gmail.com
Classifier: Programming Language :: Python :: 3
Classifier: License :: OSI Approved :: MIT License
Classifier: Operating System :: OS Independent
Requires-Python: >=3.8
License-File: LICENCE
Requires-Dist: cryptography
Requires-Dist: PyQt5
Requires-Dist: click
Requires-Dist: pyyaml
Requires-Dist: python-dotenv
Requires-Dist: colorama
Requires-Dist: pycparser
Requires-Dist: PyQt5-Qt5
Requires-Dist: PyQt5_sip
Requires-Dist: python-dotenv
Requires-Dist: PyYAML
Requires-Dist: maskpass
